anonymacy/__init__.py
anonymacy/anonymizer.py
anonymacy/conflict_resolver.py
anonymacy/context_enhancer.py
anonymacy/py.typed
anonymacy/recognizer.py
anonymacy/span_filter.py
anonymacy/util.py
anonymacy/validator.py
anonymacy-0.0.7.dist-info/METADATA
anonymacy-0.0.7.dist-info/WHEEL
anonymacy-0.0.7.dist-info/entry_points.txt
anonymacy-0.0.7.dist-info/licenses/LICENSE
anonymacy-0.0.7.dist-info/RECORD
