Metadata-Version: 2.4
Name: anonymacy
Version: 0.0.7
License-File: LICENSE
Requires-Python: <3.14,>=3.9
Requires-Dist: spacy>=3.8.7
